ForestScience/EquacoesHipsometricas.py
ForestScience/Fitossociologia.py
ForestScience/InventarioFlorestal.py
ForestScience/__init__.py
ForestScience/_modidx.py
ForestScience-0.1.0.dist-info/LICENSE
ForestScience-0.1.0.dist-info/METADATA
ForestScience-0.1.0.dist-info/WHEEL
ForestScience-0.1.0.dist-info/entry_points.txt
ForestScience-0.1.0.dist-info/top_level.txt
ForestScience-0.1.0.dist-info/RECORD
