Metadata-Version: 2.1
Name: ForestScience
Version: 0.1.0
Summary: A biblioteca Florestal
Home-page: https://github.com/gabrielfbueno/ForestScience
Author: gabrielfbueno
Author-email: gabrielfbueno@outlook.com
License: Apache Software License 2.0
Keywords: Engenharia Florestal Inventario python
Classifier: Development Status :: 4 - Beta
Classifier: Intended Audience :: Developers
Classifier: Natural Language :: Portuguese
Classifier: Programming Language :: Python :: 3.7
Classifier: Programming Language :: Python :: 3.8
Classifier: Programming Language :: Python :: 3.9
Classifier: Programming Language :: Python :: 3.10
Classifier: License :: OSI Approved :: Apache Software License
Requires-Python: >=3.7
License-File: LICENSE
Requires-Dist: pandas
Requires-Dist: numpy
Requires-Dist: scikit-learn
Requires-Dist: statsmodels
Requires-Dist: scipy
Requires-Dist: matplotlib
Requires-Dist: seaborn
Provides-Extra: dev
